main.py
mseep_weather-0.1.8.dist-info/METADATA
mseep_weather-0.1.8.dist-info/WHEEL
mseep_weather-0.1.8.dist-info/entry_points.txt
mseep_weather-0.1.8.dist-info/top_level.txt
mseep_weather-0.1.8.dist-info/RECORD
