Metadata-Version: 2.4
Name: mseep-weather
Version: 0.1.8
Summary: Add your description here
Author-email: mseep <support@skydeck.ai>
Requires-Python: >=3.10
Requires-Dist: httpx>=0.28.1
Requires-Dist: mcp[cli]>=1.6.0
Requires-Dist: python-jenkins>=1.8.2
